knittingpattern/IdCollection.py
knittingpattern/Instruction.py
knittingpattern/InstructionLibrary.py
knittingpattern/KnittingPattern.py
knittingpattern/KnittingPatternSet.py
knittingpattern/Loader.py
knittingpattern/Mesh.py
knittingpattern/Parser.py
knittingpattern/ParsingSpecification.py
knittingpattern/Prototype.py
knittingpattern/Row.py
knittingpattern/__init__.py
knittingpattern/utils.py
knittingpattern/walk.py
knittingpattern/Dumper/FileWrapper.py
knittingpattern/Dumper/__init__.py
knittingpattern/Dumper/file.py
knittingpattern/Dumper/json.py
knittingpattern/Dumper/svg.py
knittingpattern/Dumper/xml.py
knittingpattern/convert/AYABPNGBuilder.py
knittingpattern/convert/AYABPNGDumper.py
knittingpattern/convert/InstructionSVGCache.py
knittingpattern/convert/InstructionToSVG.py
knittingpattern/convert/KnittingPatternToSVG.py
knittingpattern/convert/Layout.py
knittingpattern/convert/SVGBuilder.py
knittingpattern/convert/__init__.py
knittingpattern/convert/color.py
knittingpattern/convert/image_to_knittingpattern.py
knittingpattern/convert/load_and_dump.py
knittingpattern/convert/instruction-svgs/bo.svg
knittingpattern/convert/instruction-svgs/cdd.svg
knittingpattern/convert/instruction-svgs/co.svg
knittingpattern/convert/instruction-svgs/default.svg
knittingpattern/convert/instruction-svgs/k2tog.svg
knittingpattern/convert/instruction-svgs/knit.svg
knittingpattern/convert/instruction-svgs/purl.svg
knittingpattern/convert/instruction-svgs/skp.svg
knittingpattern/convert/instruction-svgs/yo.svg
knittingpattern/convert/test/test_AYABPNGBuilder.py
knittingpattern/convert/test/test_SVGBuilder.py
knittingpattern/convert/test/test_convert.py
knittingpattern/convert/test/test_default_instruction_layout.py
knittingpattern/convert/test/test_default_svgs.py
knittingpattern/convert/test/test_images.py
knittingpattern/convert/test/test_instruction_to_svg.py
knittingpattern/convert/test/test_knittingpattern_to_png.py
knittingpattern-0.1.19.dist-info/DESCRIPTION.rst
knittingpattern-0.1.19.dist-info/METADATA
knittingpattern-0.1.19.dist-info/RECORD
knittingpattern-0.1.19.dist-info/WHEEL
knittingpattern-0.1.19.dist-info/metadata.json
knittingpattern-0.1.19.dist-info/top_level.txt
